numberify/__init__.py
numberify/numberify.py
numberify-0.0.1.data/scripts/numberify.py
numberify-0.0.1.dist-info/DESCRIPTION.rst
numberify-0.0.1.dist-info/METADATA
numberify-0.0.1.dist-info/metadata.json
numberify-0.0.1.dist-info/RECORD
numberify-0.0.1.dist-info/top_level.txt
numberify-0.0.1.dist-info/WHEEL
test/__init__.py
test/test_numberify.py
