Metadata-Version: 2.0
Name: numberify
Version: 0.0.1
Summary: Prepend each line of a file with line number
Home-page: https://github.com/darkowlzz/numberify
Author: Sunny (darkowlzz)
Author-email: indiasuny000@gmail.com
License: http://www.gnu.org/licenses/
Platform: UNKNOWN
